Workbook

Sheet Listas
A1: UF | B1: PARENTESCO | C1: TIPO_REND_TRIB | D1: TIPO_REND_ISENTO | E1: TIPO_REND_EXCLUSIVA | F1: CATEGORIA_BENS | G1: CATEGORIA_DIVIDAS | H1: TIPO_PAGAMENTO | I1: STATUS | J1: SIM_NAO | K1: BANCOS
A2: AC | B2: Cônjuge/Companheiro(a) | C2: Salário (CLT) | D2: FGTS | E2: 13º salário | F2: 01 - Imóveis | G2: 01 - Financiamento imobiliário | H2: Plano de saúde | I2: Pendente | J2: Sim | K2: Banco do Brasil
A3: AL | B3: Filho(a)/Enteado(a) | C3: Pró-labore | D3: Poupança | E3: Aplicação financeira (renda fixa) | F3: 02 - Veículos | G3: 02 - Financiamento de veículo | H3: Despesas médicas/odontológicas | I3: Em andamento | J3: Não | K3: Caixa Econômica Federal
A4: AP | B4: Filho(a) universitário até 24 anos | C4: Autônomo/RPA | D4: Dividendos de empresas | E4: Ganho de capital (venda de bens) | F4: 03 - Contas correntes/Poupança | G4: 03 - Empréstimo pessoal/consignado | H4: Educação (mensalidade) | I4: Concluído | K4: Itaú Unibanco
A5: AM | B5: Pai/Mãe/Avô/Avó | C5: Aluguel de imóvel | D5: Bolsa de estudo/pesquisa | E5: Prêmios e loterias | F5: 04 - Aplicações financeiras | G5: 04 - Cartão de crédito (saldo devedor) | H5: Previdência privada (PGBL) | K5: Bradesco
A6: BA | B6: Irmão(ã)/Neto(a) sob guarda judicial | C6: Pensão alimentícia recebida | D6: Herança/Doação recebida | E6: PLR (Participação nos Lucros) | F6: 05 - Participações societárias | G6: 05 - Outras dívidas e ônus | H6: Pensão alimentícia paga | K6: Santander
A7: CE | B7: Menor sob guarda judicial | C7: Previdência privada (PGBL) | D7: Indenização trabalhista | E7: Outros - trib. exclusiva | F7: 06 - Criptoativos | H7: Doação (incentivo fiscal) | K7: Nubank
A8: DF | B8: Ex-cônjuge (pensão alimentícia) | C8: Outros tributáveis | D8: Seguro/Pecúlio por morte | F8: 07 - Bens móveis (joias, obras de arte, etc.) | H8: Instituição de longa permanência/APAE | K8: Banco Inter
A9: ES | B9: Outros | D9: Outros isentos | F9: 08 - Outros bens e direitos | H9: Outros pagamentos dedutíveis | K9: Banco Safra
A10: GO | K10: BTG Pactual
A11: MA | K11: Banco Original
A12: MT | K12: C6 Bank
A13: MS | K13: Sicoob
A14: MG | K14: Sicredi
A15: PA | K15: Banrisul
A16: PB | K16: XP Investimentos
A17: PR | K17: Rico Investimentos
A18: PE | K18: Clear Corretora
A19: PI | K19: Mercado Pago
A20: RJ | K20: PicPay
A21: RN | K21: Empregador (informe de rendimentos)
A22: RS | K22: Outra instituição/fonte pagadora
A23: RO
A24: RR
A25: SC
A26: SP
A27: SE
A28: TO
A29: Exterior

Sheet Menu
B2: 🗂️ Controle de Dados — Declaração de Imposto de Renda
B3: Ferramenta para organizar, validar e acompanhar as informações necessárias para sua declaração de IRPF.
B5: 📌 Navegação Rápida
B6: 👤 Dados Pessoais | C6: Dados cadastrais do titular da declaração.
B7: 👨‍👩‍👧 Dependentes | C7: Cadastro de dependentes e parentesco.
B8: 💰 Rendimentos Tributáveis | C8: Salário, pró-labore, autônomo, aluguel etc.
B9: 🌿 Rendimentos Isentos | C9: FGTS, poupança, dividendos, herança etc.
B10: 🔒 Tributação Exclusiva | C10: 13º salário, aplicações, ganho de capital etc.
B11: 🏠 Bens e Direitos | C11: Imóveis, veículos, contas, aplicações etc.
B12: 💳 Dívidas e Ônus | C12: Financiamentos e empréstimos em aberto.
B13: 🧾 Pagamentos e Doações | C13: Saúde, educação, previdência, doações etc.
B14: 🏦 Controle de Informes | C14: Checklist de informes de rendimento por fonte.
B15: 📊 Resumo e Status | C15: Painel com totais e progresso do preenchimento.
B17: ℹ️ Como usar esta planilha
B18: 1. Use os links acima para navegar entre as seções. Cada aba possui um link "Voltar ao Menu" no topo. 2. Preencha apenas as células em branco das tabelas — colunas com lista suspensa (setinha) devem ser preenchidas selecionando uma opção. 3. A primeira linha de cada tabela é um EXEMPLO (em cinza/itálico) — substitua ou apague antes de preencher seus dados reais. 4. A aba "Resumo e Status" consolida os totais e mostra o progresso do preenchimento automaticamente.
B24: Esta planilha é uma ferramenta de organização pessoal de dados e não substitui o programa oficial da Receita Federal (IRPF) nem constitui orientação tributária. Consulte um contador para validar sua situação fiscal.

Sheet DadosPessoais
B1: 👤 Dados Pessoais
B2: ◀ Voltar ao Menu
B4: Identificação do Titular
B5: Campo | C5: Preencha aqui | D5: Formato esperado (exemplo)
B6: Nome completo | D6: João da Silva Santos
B7: CPF | D7: 000.000.000-00
B8: Data de nascimento | D8: 01/01/1990
B9: Título de eleitor | D9: 0000 0000 0000
B10: Estado civil | D10: Solteiro(a) / Casado(a) / etc.
B11: Ocupação/Profissão | D11: Analista Comercial
B12: Naturalidade (UF) | D12: SP
B13: Endereço completo | D13: Rua, número, bairro, cidade
B14: CEP | D14: 00000-000
B15: Telefone | D15: (00) 00000-0000
B16: E-mail | D16: nome@email.com
B18: Preencha a coluna "Preencha aqui" (amarela). A coluna "Formato esperado" é apenas uma referência e não precisa ser apagada. O campo "Naturalidade (UF)" possui lista suspensa.

Sheet Dependentes
B1: 👨‍👩‍👧 Dependentes
B2: ◀ Voltar ao Menu
B4: Cadastro de Dependentes
B5: Nome completo | C5: CPF | D5: Data de nascimento | E5: Parentesco | F5: Observações
B6: Maria da Silva Santos | C6: 000.000.000-00 | D6: 15/03/2015 | E6: Filho(a)/Enteado(a) | F6: Estuda em período integral
B17: A primeira linha é um exemplo (cinza) — apague antes de inserir seus dependentes reais. A coluna "Parentesco" possui lista suspensa.

Sheet RendTributaveis
B1: 💰 Rendimentos Tributáveis
B2: ◀ Voltar ao Menu
B4: Lançamento de Rendimentos Tributáveis (salário, pró-labore, autônomo, aluguel etc.)
B5: Fonte pagadora | C5: CNPJ/CPF da fonte | D5: Tipo de rendimento | E5: Mês de referência | F5: Valor recebido (R$) | G5: IRRF retido (R$)
B6: Empresa XYZ Ltda | C6: 00.000.000/0001-00 | D6: Salário (CLT) | E6: 01/2026 | F6: 5000 | G6: 380.5
B27: TOTAL | F27: =SUM(F7:F25) -> 0 | G27: =SUM(G7:G25) -> 0
B29: A primeira linha é um EXEMPLO (cinza/itálico) — apague antes de lançar seus dados reais. O total (soma da linha 7 em diante) é calculado automaticamente e não considera a linha de exemplo.

Sheet RendIsentos
B1: 🌿 Rendimentos Isentos e Não Tributáveis
B2: ◀ Voltar ao Menu
B4: Lançamento de Rendimentos Isentos e Não Tributáveis
B5: Fonte pagadora | C5: CNPJ/CPF da fonte | D5: Tipo de rendimento | E5: Data de recebimento | F5: Valor recebido (R$)
B6: Caixa Econômica Federal | C6: 00.000.000/0001-00 | D6: FGTS | E6: 10/03/2026 | F6: 3200
B27: TOTAL | F27: =SUM(F7:F25) -> 0
B29: A primeira linha é um EXEMPLO (cinza/itálico) — apague antes de lançar seus dados reais. O total (soma da linha 7 em diante) é calculado automaticamente e não considera a linha de exemplo.

Sheet RendExclusiva
B1: 🔒 Rendimentos Sujeitos à Tributação Exclusiva
B2: ◀ Voltar ao Menu
B4: Lançamento de Rendimentos com Tributação Exclusiva/Definitiva
B5: Fonte pagadora | C5: CNPJ/CPF da fonte | D5: Tipo de rendimento | E5: Mês de referência | F5: Valor recebido (R$) | G5: IRRF retido (R$)
B6: Empresa XYZ Ltda | C6: 00.000.000/0001-00 | D6: 13º salário | E6: 12/2025 | F6: 5000 | G6: 715.29
B27: TOTAL | F27: =SUM(F7:F25) -> 0 | G27: =SUM(G7:G25) -> 0
B29: A primeira linha é um EXEMPLO (cinza/itálico) — apague antes de lançar seus dados reais. O total (soma da linha 7 em diante) é calculado automaticamente e não considera a linha de exemplo.

Sheet BensDireitos
B1: 🏠 Bens e Direitos
B2: ◀ Voltar ao Menu
B4: Inventário de Bens e Direitos (posição em 31 de dezembro)
B5: Categoria | C5: Descrição do bem | D5: Localização (UF) | E5: Situação em 31/12 (ano anterior) R$ | F5: Situação em 31/12 (ano atual) R$
B6: 01 - Imóveis | C6: Apartamento residencial, matrícula 00.000, Rua Exemplo, 123 | D6: SP | E6: 250000 | F6: 250000
B32: TOTAL | E32: =SUM(E7:E30) -> 0 | F32: =SUM(F7:F30) -> 0
B34: A primeira linha é um EXEMPLO (cinza/itálico) — apague antes de lançar seus dados reais. O total (soma da linha 7 em diante) é calculado automaticamente e não considera a linha de exemplo.

Sheet DividasOnus
B1: 💳 Dívidas e Ônus
B2: ◀ Voltar ao Menu
B4: Inventário de Dívidas e Ônus Reais (posição em 31 de dezembro)
B5: Categoria | C5: Descrição | D5: Credor/Instituição | E5: Saldo devedor em 31/12 (ano anterior) R$ | F5: Saldo devedor em 31/12 (ano atual) R$
B6: 01 - Financiamento imobiliário | C6: Financiamento do apartamento - 180 parcelas | D6: Caixa Econômica Federal | E6: 180000 | F6: 172000
B22: TOTAL | E22: =SUM(E7:E20) -> 0 | F22: =SUM(F7:F20) -> 0
B24: A primeira linha é um EXEMPLO (cinza/itálico) — apague antes de lançar seus dados reais. O total (soma da linha 7 em diante) é calculado automaticamente e não considera a linha de exemplo.

Sheet Pagamentos
B1: 🧾 Pagamentos e Doações
B2: ◀ Voltar ao Menu
B4: Lançamento de Pagamentos e Doações Dedutíveis
B5: Tipo de pagamento | C5: Beneficiário | D5: CPF/CNPJ do beneficiário/prestador | E5: Data do pagamento | F5: Valor pago (R$)
B6: Plano de saúde | C6: Operadora de Saúde XYZ | D6: 00.000.000/0001-00 | E6: 10/06/2026 | F6: 850
B27: TOTAL | F27: =SUM(F7:F25) -> 0
B29: A primeira linha é um EXEMPLO — apague antes de lançar seus dados reais. Guarde os recibos e notas fiscais correspondentes: a Receita Federal pode solicitá-los.

Sheet Informes
B1: 🏦 Controle de Informes de Rendimento
B2: ◀ Voltar ao Menu
B4: Checklist de Informes por Fonte Pagadora / Instituição
B5: Instituição/Fonte pagadora | C5: Tipo de documento | D5: Recebido? | E5: Data de recebimento | F5: Observações
B6: Banco Itaú Unibanco | C6: Informe de Rendimentos - conta corrente | D6: Sim | E6: 15/02/2026 | F6: Baixado no app do banco
B27: Total de informes cadastrados: | D27: =COUNTA(B7:B25) -> 0
B28: Informes já recebidos: | D28: =COUNTIF(D7:D25,"Sim") -> 0
B29: Informes pendentes: | D29: =COUNTIF(D7:D25,"Não") -> 0
B31: A primeira linha é um exemplo. Cadastre cada fonte pagadora (bancos, corretoras, empregador) e marque "Sim"/"Não" conforme for recebendo os informes de rendimento.

Sheet Resumo
B1: 📊 Resumo e Status do Preenchimento
B2: ◀ Voltar ao Menu
B4: Totais Financeiros (ano corrente)
B5: Categoria | C5: Total (R$) | D5: Registros lançados
B6: Rendimentos Tributáveis | C6: =SUM(RendTributaveis!F7:F25) -> 0 | D6: =COUNTA(RendTributaveis!B7:B25) -> 0
B7: Rendimentos Isentos | C7: =SUM(RendIsentos!F7:F25) -> 0 | D7: =COUNTA(RendIsentos!B7:B25) -> 0
B8: Tributação Exclusiva | C8: =SUM(RendExclusiva!F7:F25) -> 0 | D8: =COUNTA(RendExclusiva!B7:B25) -> 0
B9: Bens e Direitos (posição atual) | C9: =SUM(BensDireitos!F7:F30) -> 0 | D9: =COUNTA(BensDireitos!B7:B30) -> 0
B10: Dívidas e Ônus (saldo atual) | C10: =SUM(DividasOnus!F7:F20) -> 0 | D10: =COUNTA(DividasOnus!B7:B20) -> 0
B11: Pagamentos e Doações | C11: =SUM(Pagamentos!F7:F25) -> 0 | D11: =COUNTA(Pagamentos!B7:B25) -> 0
B13: Progresso Geral do Preenchimento
B14: Dados pessoais preenchidos | C14: =IF(DadosPessoais!C6<>"","Concluído","Pendente") -> Pendente
B15: Dependentes cadastrados | C15: =COUNTA(Dependentes!B7:B16) -> 0
B16: Rendimentos tributáveis lançados | C16: =COUNTA(RendTributaveis!B7:B25) -> 0
B17: Bens e direitos lançados | C17: =COUNTA(BensDireitos!B7:B30) -> 0
B18: Informes cadastrados | C18: =COUNTA(Informes!B7:B25) -> 0
B19: Informes recebidos | C19: =COUNTIF(Informes!D7:D25,"Sim") -> 0
B20: Informes pendentes | C20: =COUNTIF(Informes!D7:D25,"Não") -> 0
B22: Os totais e contagens são calculados automaticamente a partir das demais abas. Lembre-se de apagar as linhas de exemplo (em cinza) em cada tabela para que os totais reflitam apenas os seus dados reais.
