Workbook

Sheet Dados_Brutos
A1: 🚗 Dados Brutos — Base Porsche (como recebida)
A2: << Voltar ao Dashboard
A4: ID Venda | B4: Data (bruta) | C4: Cliente (bruto) | D4: Modelo | E4: Ano (bruto) | F4: Preço (bruto) | G4: Quilometragem (bruta) | H4: Pagamento (bruto) | I4: Cidade (bruta) | J4: Estado (bruto) | K4: Vendedor (bruto) | L4: Status (bruto)
A5: 6 | B5: 2024-02-30 | C5: Michael Adams | D5: 718 Cayman | E5: 2022 | F5: $79,500.00 | G5: 9,800 miles | H5: Credit card | I5: boston | J5: ma | K5: kevin | L5: delivered
A6: 7 | B6: 03/14/2024 | C6: SOPHIA Miller | D6: 911 Turbo S | E6: twenty twenty four | F6: 235000 USD | G6: 1.200 mi | H6: wire transfer | I6: Seattle | J6: Washington | K6: AMANDA scott | L6: DELIVERED
A7: 8 | B7: 2024-04-18 00:00:00 | C7: Daniel-Jones | D7: Cayenne Coupe | E7: 2023 | F7: USD 112.750 | G7: Miles: 6,400 | H7: Financing plan | I7: austin | J7: tx | K7: Brian Hall | L7: in Transit
A8: 9 | B8: April 31st, 2024 | C8: Olivia Brown | D8: Macan S | E8: 2021 | F8: 68.900 dollars | G8: 28 | H8: CASH | I8: Denver | J8: colorado | K8: jessica | L8: Pending
A9: 10 | B9: 2024-05-22 00:00:00 | C9: Ethan Wilson | D9: Taycan 4S | E9: 2024 | F9: $121k | G9: zero miles | H9: bank-transfer | I9: los angeles | J9: ca | K9: Thomas King | L9: delivered!!!
A10: 11 | B10: 2024-08-06 00:00:00 | C10: Ava Martinez | D10: Panamera 4 | E10: 20-23 | F10: 104,500 USD | G10: 14.500 miles | H10: Credit Card | I10: Miami | J10: FL | K10: LISA ray | L10: cancelled
A11: 12 | B11: 2024.07.11 | C11: Noah Davis | D11: 911 Carrera S | E11: 2020 | F11: USD $96,300 | G11: 41,000mi | H11: lease | I11: new york | J11: New York | K11: Mark Evans | L11: DELIVERD
A12: 13 | B12: 2024/15/07 | C12: Isabella Garcia | D12: Cayenne E-Hybrid | E12: 2022 | F12: $89.750,00 | G12: KM 18,900 | H12: bank wire | I12: San Diego | J12: CA | K12: nancy reed | L12: pending approval
A13: 14 | B13: 08/19/24 | C13: Liam Rodriguez | D13: 718 Boxster | E13: two thousand twenty one | F13: 73500 | G13: 22,300 miles | H13: debit card | I13: chicago | J13: IL | K13: George Bell | L13: shipped
A14: 15 | B14: 2024-09-02 00:00:00 | C14: Mia Hernandez | D14: Macan GTS | E14: 2024 | F14: 95,000 dollars | G14: 3.500 mi | H14: Financing | I14: phoenix | J14: arizona | K14: Helen Brooks | L14: IN TRANSIT
A15: 16 | B15: September 17, 2024 | C15: James Lopez | D15: Taycan Turbo | E15: 2023 | F15: $153,200.50 | G15: 11 | H15: ACH payment | I15: dallas | J15: tx | K15: samuel price | L15: delivered
... A104: 105 | B104: 2027.10.01 | C104: Madison Powell | D104: 911 Dakar | E104: twenty twenty four | F104: $271,700 | G104: 1,050 miles | H104: Leasing | I104: new orleans | J104: la | K104: Steve Ross | L104: Delivered
A106: Esta aba reproduz a base exatamente como recebida (texto livre, formatos inconsistentes de data/preço/quilometragem, capitalização irregular etc.). É a ENTRADA do Agente de Tratamento de Dados — veja a aba Dados_Tratados.

Sheet Dados_Tratados
A1: ✅ Dados Tratados — Saída do Agente de Tratamento de Dados
A2: << Voltar ao Dashboard
A3: Gerada automaticamente pelo script agente_tratamento_dados.py — não editar manualmente.
A4: ID Venda | B4: Data da Venda | C4: Cliente | D4: Modelo | E4: Ano | F4: Preço (R$) | G4: Quilometragem (mi) | H4: Pagamento | I4: Cidade | J4: UF | K4: Vendedor | L4: Status Entrega | M4: Ano-Mês
A5: 6 | B5: Data inválida | C5: Michael Adams | D5: 718 Cayman | E5: 2022 | F5: 79500 | G5: 9800 | H5: Credit Card | I5: Boston | J5: MA | K5: Kevin Brown | L5: Delivered
A6: 7 | B6: 2024-03-14 | C6: Sophia Miller | D6: 911 Turbo S | E6: 2024 | F6: 235000 | G6: 1200 | H6: Wire Transfer | I6: Seattle | J6: WA | K6: Amanda Scott | L6: Delivered | M6: 2024-03
A7: 8 | B7: 2024-04-18 | C7: Daniel Jones | D7: Cayenne Coupe | E7: 2023 | F7: 112750 | G7: 6400 | H7: Financing | I7: Austin | J7: TX | K7: Brian Hall | L7: In Transit | M7: 2024-04
A8: 9 | B8: Data inválida | C8: Olivia Brown | D8: Macan S | E8: 2021 | F8: 68900 | G8: 28 | H8: Cash | I8: Denver | J8: CO | K8: Jessica White | L8: Pending
A9: 10 | B9: 2024-05-22 | C9: Ethan Wilson | D9: Taycan 4S | E9: 2024 | F9: 121000 | G9: 0 | H9: Bank Transfer | I9: Los Angeles | J9: CA | K9: Thomas King | L9: Delivered | M9: 2024-05
A10: 11 | B10: 2024-08-06 | C10: Ava Martinez | D10: Panamera 4 | E10: 2023 | F10: 104500 | G10: 14500 | H10: Credit Card | I10: Miami | J10: FL | K10: Lisa Ray | L10: Cancelled | M10: 2024-08
A11: 12 | B11: 2024-07-11 | C11: Noah Davis | D11: 911 Carrera S | E11: 2020 | F11: 96300 | G11: 41000 | H11: Lease | I11: New York | J11: NY | K11: Mark Evans | L11: Delivered | M11: 2024-07
A12: 13 | B12: Data inválida | C12: Isabella Garcia | D12: Cayenne E-Hybrid | E12: 2022 | F12: 89750 | G12: 11744 | H12: Wire Transfer | I12: San Diego | J12: CA | K12: Nancy Reed | L12: Pending Approval
A13: 14 | B13: 2024-08-19 | C13: Liam Rodriguez | D13: 718 Boxster | E13: 2021 | F13: 73500 | G13: 22300 | H13: Debit Card | I13: Chicago | J13: IL | K13: George Bell | L13: Shipped | M13: 2024-08
A14: 15 | B14: 2024-09-02 | C14: Mia Hernandez | D14: Macan GTS | E14: 2024 | F14: 95000 | G14: 3500 | H14: Financing | I14: Phoenix | J14: AZ | K14: Helen Brooks | L14: In Transit | M14: 2024-09
A15: 16 | B15: 2024-09-17 | C15: James Lopez | D15: Taycan Turbo | E15: 2023 | F15: 153200.5 | G15: 11 | H15: ACH Payment | I15: Dallas | J15: TX | K15: Samuel Price | L15: Delivered | M15: 2024-09
A16: 17 | B16: Data inválida | C16: Charlotte Young | D16: 911 GT3 | E16: 2024 | F16: 241000 | G16: 750 | H16: Wire Transfer | I16: Las Vegas | J16: NV | K16: Peter Ford | L16: Pending
A17: 18 | B17: 2024-05-11 | C17: Benjamin Allen | D17: Panamera Turbo S | E17: 2022 | F17: 132000 | G17: 19250 | H17: Cash | I17: San Jose | J17: CA | K17: Angela Green | L17: Delivered | M17: 2024-05
A18: 19 | B18: 2024-12-12 | C18: Amelia King | D18: Cayenne Turbo GT | E18: 2024 | F18: 188000 | G18: 2100 | H18: Crypto Payment | I18: Houston | J18: TX | K18: Victor Stone | L18: Awaiting Delivery | M18: 2024-12
A19: 20 | B19: 2024-12-25 | C19: Lucas Wright | D19: 911 Carrera Cabriolet | E19: 2023 | F19: 127800 | G19: 12000 | H19: Credit Card | I19: Atlanta | J19: GA | K19: Rachel Turner | L19: Delivered | M19: 2024-12
A20: 21 | B20: 2025-01-06 | C20: Harper Scott | D20: Macan | E20: 2021 | F20: 58900 | G20: 33700 | H20: Bank Transfer | I20: Orlando | J20: FL | K20: Chris Moore | L20: Pending | M20: 2025-01
A21: 22 | B21: Data inválida | C21: Henry Torres | D21: 718 Spyder RS | E21: 2024 | F21: 164000 | G21: 900 | H21: Financing | I21: Portland | J21: OR | K21: Laura Hill | L21: In Transit
A22: 23 | B22: 2025-02-14 | C22: Evelyn Nguyen | D22: Taycan Cross Turismo | E22: 2023 | F22: 118500 | G22: 7800 | H22: Wire Transfer | I22: Charlotte | J22: NC | K22: Martin Young | L22: Delivered | M22: 2025-02
A23: 24 | B23: Data inválida | C23: Alexander Flores | D23: Cayenne S | E23: 2022 | F23: 91300 | G23: 16000 | H23: Credit Card | I23: Nashville | J23: TN | K23: Diana Cooper | L23: Pending
A24: 25 | B24: 2025-03-21 | C24: Abigail Carter | D24: 911 Targa 4S | E24: 2024 | F24: 158750 | G24: 2500 | H24: Lease | I24: Minneapolis | J24: MN | K24: Steve Gray | L24: Delivered | M24: 2025-03
A25: 26 | B25: 2025-03-28 | C25: Jack Mitchell | D25: Panamera | E25: 2020 | F25: 72000 | G25: 49000 | H25: Bank Transfer | I25: Philadelphia | J25: PA | K25: Olivia Ross | L25: Cancelled | M25: 2025-03
A26: 27 | B26: 2025-04-09 | C26: Emily Perez | D26: Macan Electric | E26: 2025 | F26: 86500 | G26: 0 | H26: Wire Transfer | I26: San Antonio | J26: TX | K26: Patrick Wood | L26: Delivered | M26: 2025-04
A27: 28 | B27: Data inválida | C27: William Roberts | D27: 911 Dakar | E27: 2024 | F27: 270000 | G27: 1050 | H27: Cash | I27: Salt Lake City | J27: UT | K27: Karen Diaz | L27: Awaiting Pickup
A28: 29 | B28: 2025-05-12 | C28: Sofia Turner | D28: Taycan GTS | E28: 2023 | F28: 139000 | G28: 6250 | H28: Financing | I28: Raleigh | J28: NC | K28: Justin Cox | L28: In Transit | M28: 2025-05
A29: 30 | B29: 2025-06-18 | C29: Mason Phillips | D29: Cayenne | E29: 2021 | F29: 76800 | G29: 38400 | H29: Credit Card | I29: Detroit | J29: MI | K29: Betty Ward | L29: Delivered | M29: 2025-06
A30: 31 | B30: Data inválida | C30: Ella Campbell | D30: 718 Cayman GT4 RS | E30: 2024 | F30: 173600 | G30: 400 | H30: Wire Transfer | I30: Columbus | J30: OH | K30: Gary Reed | L30: Pending
A31: 32 | B31: 2025-07-07 | C31: Logan Parker | D31: 911 Carrera GTS | E31: 2022 | F31: 119900 | G31: 13600 | H31: Cash | I31: Indianapolis | J31: IN | K31: Maria Foster | L31: Delivered | M31: 2025-07
A32: 33 | B32: 2025-07-22 | C32: Grace Evans | D32: Panamera 4 E-Hybrid | E32: 2023 | F32: 109250 | G32: 8900 | H32: Lease | I32: Fort Worth | J32: TX | K32: Harold Bennett | L32: In Transit | M32: 2025-07
A33: 34 | B33: 2025-08-14 | C33: Jacob Edwards | D33: Macan T | E33: 2022 | F33: 82000 | G33: 21750 | H33: Wire Transfer | I33: Jacksonville | J33: FL | K33: Teresa Cook | L33: Delivered | M33: 2025-08
A34: 35 | B34: 2025-09-01 | C34: Victoria Collins | D34: Taycan Turbo S | E34: 2025 | F34: 214000 | G34: 0 | H34: Crypto Payment | I34: San Diego | J34: CA | K34: Frank Morgan | L34: Pending Review | M34: 2025-09
A35: 36 | B35: Data inválida | C35: Andrew Simmons | D35: 911 Carrera | E35: 2024 | F35: 124500 | G35: 4800 | H35: Credit Card | I35: Tampa | J35: FL | K35: Natalie | L35: Delivered
A36: 37 | B36: 2025-09-18 | C36: Chloe Bennett | D36: Cayenne S | E36: 2023 | F36: 98200 | G36: 12200 | H36: Bank Transfer | I36: Sacramento | J36: CA | K36: Eric Woods | L36: Pending | M36: 2025-09
A37: 38 | B37: 2025-10-04 | C37: Ryan Cooper | D37: Macan | E37: 2022 | F37: 67500 | G37: 24100 | H37: Financing | I37: Cleveland | J37: OH | K37: Patricia Fox | L37: Delivered | M37: 2025-10
A38: 39 | B38: 2025-10-12 | C38: Hannah Reed | D38: Taycan | E38: 2025 | F38: 116900 | G38: 0 | H38: Wire Transfer | I38: Milwaukee | J38: WI | K38: Alan Price | L38: In Transit | M38: 2025-10
A39: 40 | B39: 2025-10-29 | C39: Dylan Parker | D39: Panamera 4S | E39: 2024 | F39: 112000 | G39: 10 | H39: Cash | I39: Kansas City | J39: MO | K39: Sandra Hill | L39: Delivered | M39: 2025-10
A40: 41 | B40: 2025-02-11 | C40: Lily Coleman | D40: 718 Boxster | E40: 2021 | F40: 74000 | G40: 31000 | H40: Debit Card | I40: Omaha | J40: NE | K40: Victor Lee | L40: Cancelled | M40: 2025-02
A41: 42 | B41: 2025-11-16 | C41: Nathan Hughes | D41: 911 Turbo | E41: 2024 | F41: 198300 | G41: 2400 | H41: Wire Transfer | I41: Albuquerque | J41: NM | K41: Monica Green | L41: Awaiting Delivery | M41: 2025-11
A42: 43 | B42: Data inválida | C42: Zoe Foster | D42: Cayenne Coupe | E42: 2023 | F42: 103750 | G42: 6773 | H42: Wire Transfer | I42: Tucson | J42: AZ | K42: Gregory Adams | L42: Pending Approval
A43: 44 | B43: Data inválida | C43: Caleb Ward | D43: Macan GTS | E43: 2024 | F43: 93600 | G43: 5800 | H43: Financing | I43: Fresno | J43: CA | K43: Laura West | L43: Shipped
A44: 45 | B44: 2025-12-07 | C44: Stella Brooks | D44: Taycan 4S | E44: 2025 | F44: 129000 | G44: 0 | H44: ACH Payment | I44: Virginia Beach | J44: VA | K44: Henry King | L44: In Transit | M44: 2025-12
A45: 46 | B45: 2025-12-22 | C45: Owen Bryant | D45: Panamera Turbo | E45: 2022 | F45: 136000 | G45: 18400 | H45: Credit Card | I45: Colorado Springs | J45: CO | K45: Amber Clark | L45: Delivered | M45: 2025-12
A46: 47 | B46: Data inválida | C46: Nora Simmons | D46: 911 GT3 RS | E46: 2024 | F46: 286500 | G46: 700 | H46: Wire Transfer | I46: Arlington | J46: TX | K46: Peter Lane | L46: Pending
A47: 48 | B47: 2026-01-08 | C47: Isaac Butler | D47: Cayenne E-Hybrid | E47: 2023 | F47: 92800 | G47: 15000 | H47: Lease | I47: Bakersfield | J47: CA | K47: Grace Morris | L47: Delivered | M47: 2026-01
A48: 49 | B48: 2026-01-15 | C48: Leah Henderson | D48: Macan T | E48: 2022 | F48: 72400 | G48: 19750 | H48: Cash | I48: Mesa | J48: AZ | K48: Kyle Perry | L48: Awaiting Pickup | M48: 2026-01
A49: 50 | B49: 2026-01-28 | C49: Christian Bailey | D49: Taycan Turbo | E49: 2025 | F49: 158500 | G49: 3200 | H49: Crypto Payment | I49: Atlanta | J49: GA | K49: Megan Reed | L49: Delivered | M49: 2026-01
A50: 51 | B50: 2026-02-03 | C50: Audrey Russell | D50: 718 Cayman | E50: 2021 | F50: 69900 | G50: 27600 | H50: Bank Transfer | I50: Long Beach | J50: CA | K50: Carl Simmons | L50: Pending | M50: 2026-02
A51: 52 | B51: Data inválida | C51: Hunter Griffin | D51: 911 Targa 4 | E51: 2024 | F51: 141250 | G51: 2100 | H51: Financing | I51: Oakland | J51: CA | K51: Linda Cole | L51: In Transit
A52: 53 | B52: 2026-02-19 | C52: Scarlett Diaz | D52: Panamera | E52: 2020 | F52: 71500 | G52: 52000 | H52: Wire Transfer | I52: Tulsa | J52: OK | K52: Martin Brooks | L52: Delivered | M52: 2026-02
A53: 54 | B53: 2026-02-25 | C53: Eli Jenkins | D53: Cayenne Turbo | E53: 2023 | F53: 146800 | G53: 11300 | H53: Credit Card | I53: Wichita | J53: KS | K53: Diana Long | L53: Pending | M53: 2026-02
A54: 55 | B54: 2026-03-01 | C54: Madison Powell | D54: Macan Electric | E54: 2025 | F54: 89700 | G54: 0 | H54: Lease | I54: New Orleans | J54: LA | K54: Steve Ross | L54: Delivered | M54: 2026-03
A55: 56 | B55: 2026-03-14 | C55: Adrian Sanders | D55: 911 Carrera S | E55: 2022 | F55: 104600 | G55: 15900 | H55: Bank Transfer | I55: Honolulu | J55: HI | K55: Olivia Cruz | L55: Cancelled | M55: 2026-03
A56: 57 | B56: Data inválida | C56: Penelope Barnes | D56: Taycan GTS | E56: 2024 | F56: 142000 | G56: 6600 | H56: Wire Transfer | I56: Anaheim | J56: CA | K56: Patrick Wood | L56: Delivered
A57: 58 | B57: 2026-04-08 | C57: Nolan Fisher | D57: Cayenne | E57: 2021 | F57: 78400 | G57: 40250 | H57: Cash | I57: Henderson | J57: NV | K57: Karen Stone | L57: Awaiting Review | M57: 2026-04
A58: 59 | B58: Data inválida | C58: Layla Marshall | D58: 718 Spyder RS | E58: 2025 | F58: 169000 | G58: 850 | H58: Financing | I58: Lexington | J58: KY | K58: Justin Fox | L58: In Transit
A59: 60 | B59: 2026-04-21 | C59: Gabriel Owens | D59: 911 Dakar | E59: 2024 | F59: 268900 | G59: 1400 | H59: Credit Card | I59: Riverside | J59: CA | K59: Betty James | L59: Delivered | M59: 2026-04
A60: 61 | B60: 2026-04-29 | C60: Victoria Hart | D60: Panamera 4 | E60: 2023 | F60: 101300 | G60: 12700 | H60: Wire Transfer | I60: Corpus Christi | J60: TX | K60: Gary Price | L60: Pending | M60: 2026-04
A61: 62 | B61: 2026-05-05 | C61: Julian Stone | D61: Macan S | E61: 2021 | F61: 66750 | G61: 29800 | H61: Cash | I61: St. Louis | J61: MO | K61: Maria Green | L61: Delivered | M61: 2026-05
A62: 63 | B62: 2026-05-14 | C62: Brooklyn Webb | D62: Taycan Cross Turismo | E62: 2024 | F62: 127900 | G62: 7500 | H62: Lease | I62: Pittsburgh | J62: PA | K62: Harold Young | L62: In Transit | M62: 2026-05
A63: 64 | B63: 2026-05-23 | C63: Aaron Kim | D63: Cayenne Turbo GT | E63: 2025 | F63: 200000 | G63: 1950 | H63: Wire Transfer | I63: Cincinnati | J63: OH | K63: Teresa Ward | L63: Delivered | M63: 2026-05
A64: 65 | B64: 2026-06-02 | C64: Claire Watson | D64: 911 Carrera Cabriolet | E64: 2023 | F64: 132000 | G64: 8800 | H64: Crypto Payment | I64: Anchorage | J64: AK | K64: Frank Reed | L64: Pending Review | M64: 2026-06
A65: 66 | B65: 2026-06-15 | C65: Sebastian Brooks | D65: 718 Cayman GT4 RS | E65: 2024 | F65: 176400 | G65: 600 | H65: Credit Card | I65: Plano | J65: TX | K65: Angela Moore | L65: Delivered | M65: 2026-06
A66: 67 | B66: Data inválida | C66: Bella Ramirez | D66: Panamera 4 E-Hybrid | E66: 2022 | F66: 108500 | G66: 16200 | H66: Bank Transfer | I66: Newark | J66: NJ | K66: Rachel West | L66: Cancelled
A67: 68 | B67: 2026-07-07 | C67: Miles Peterson | D67: Macan | E67: 2021 | F67: 59000 | G67: 36000 | H67: Financing | I67: Greensboro | J67: NC | K67: Thomas Fox | L67: Awaiting Delivery | M67: 2026-07
A68: 69 | B68: 2026-07-20 | C68: Skylar Rogers | D68: Taycan Turbo S | E68: 2025 | F68: 218000 | G68: 0 | H68: Wire Transfer | I68: Lincoln | J68: NE | K68: Lisa Dunn | L68: Pending | M68: 2026-07
A69: 70 | B69: Data inválida | C69: Dominic Kelly | D69: Cayenne S | E69: 2024 | F69: 99950 | G69: 5300 | H69: Debit Card | I69: Jersey City | J69: NJ | K69: Brian Allen | L69: Delivered
A70: 71 | B70: 2026-04-08 | C70: Lucy Howard | D70: 911 Carrera GTS | E70: 2024 | F70: 121750 | G70: 5872 | H70: Credit Card | I70: Chandler | J70: AZ | K70: George Hall | L70: Delivered | M70: 2026-04
A71: 72 | B71: 2026-08-18 | C71: Everett Cox | D71: 718 Boxster GTS | E71: 2023 | F71: 91500 | G71: 13300 | H71: Lease | I71: Reno | J71: NV | K71: Helen King | L71: Shipped | M71: 2026-08
A72: 73 | B72: 2026-08-31 | C72: Maya Rivera | D72: Panamera Turbo S | E72: 2022 | F72: 134000 | G72: 20100 | H72: Wire Transfer | I72: Buffalo | J72: NY | K72: Samuel Price | L72: In Transit | M72: 2026-08
A73: 74 | B73: 2026-09-09 | C73: Connor Ward | D73: Macan GTS | E73: 2024 | F73: 96800 | G73: 0 | H73: ACH Payment | I73: Durham | J73: NC | K73: Peter Ford | L73: Delivered | M73: 2026-09
A74: 75 | B74: 2026-09-17 | C74: Eliana Bell | D74: Taycan 4S | E74: 2025 | F74: 131600 | G74: 2900 | H74: Wire Transfer | I74: Laredo | J74: TX | K74: Angela Green | L74: Pending Approval | M74: 2026-09
A75: 76 | B75: 2026-09-28 | C75: Cameron Murphy | D75: Cayenne E-Hybrid | E75: 2023 | F75: 94300 | G75: 13100 | H75: Cash | I75: Madison | J75: WI | K75: Victor Stone | L75: Delivered | M75: 2026-09
A76: 77 | B76: 2026-10-06 | C76: Ariana Cook | D76: 911 Turbo S | E76: 2025 | F76: 242000 | G76: 1100 | H76: Crypto Payment | I76: Lubbock | J76: TX | K76: Rachel Turner | L76: Awaiting Pickup | M76: 2026-10
A77: 78 | B77: 2026-10-16 | C77: Wesley Morgan | D77: 718 Cayman S | E77: 2022 | F77: 82750 | G77: 22500 | H77: Credit Card | I77: Toledo | J77: OH | K77: Chris Moore | L77: Cancelled | M77: 2026-10
A78: 79 | B78: 2026-10-29 | C78: Naomi Peterson | D78: Macan Electric | E78: 2026 | F78: 91300 | G78: 0 | H78: Wire Transfer | I78: Irvine | J78: CA | K78: Laura Hill | L78: Delivered | M78: 2026-10
A79: 80 | B79: 2026-11-03 | C79: Jason Perry | D79: Panamera | E79: 2021 | F79: 79900 | G79: 44800 | H79: Financing | I79: Garland | J79: TX | K79: Martin Young | L79: Pending | M79: 2026-11
A80: 81 | B80: Data inválida | C80: Riley Flores | D80: Cayenne Coupe | E80: 2024 | F80: 111000 | G80: 6700 | H80: Bank Transfer | I80: Irving | J80: TX | K80: Diana Cooper | L80: In Transit
A81: 82 | B81: 2026-12-11 | C81: Hazel Long | D81: 911 Targa 4S | E81: 2023 | F81: 156500 | G81: 4200 | H81: Cash | I81: Chesapeake | J81: VA | K81: Steve Gray | L81: Delivered | M81: 2026-12
A82: 83 | B82: 2026-12-24 | C82: Easton Bailey | D82: Taycan | E82: 2025 | F82: 119900 | G82: 1250 | H82: Lease | I82: Scottsdale | J82: AZ | K82: Olivia Ross | L82: Pending | M82: 2026-12
A83: 84 | B83: Data inválida | C83: Aurora Cooper | D83: Macan T | E83: 2022 | F83: 73200 | G83: 18600 | H83: Wire Transfer | I83: Norfolk | J83: VA | K83: Patrick Wood | L83: Delivered
A84: 85 | B84: 2026-12-28 | C84: Colton Richardson | D84: 911 GT3 | E84: 2024 | F84: 224000 | G84: 3000 | H84: Wire Transfer | I84: Boise | J84: ID | K84: Karen Diaz | L84: Awaiting Delivery | M84: 2026-12
A85: 86 | B85: 2027-01-15 | C85: Mason Stewart | D85: 911 Carrera | E85: 2024 | F85: 126900 | G85: 7200 | H85: Credit Card | I85: Orlando | J85: FL | K85: Kevin Brown | L85: Delivered | M85: 2027-01
A86: 87 | B86: 2027-01-29 | C86: Harper Reed | D86: Cayenne | E86: 2023 | F86: 84500 | G86: 21400 | H86: Bank Transfer | I86: San Jose | J86: CA | K86: Amanda Lee | L86: Pending | M86: 2027-01
A87: 88 | B87: 2027-02-11 | C87: Tyler Morris | D87: Macan S | E87: 2022 | F87: 69800 | G87: 26300 | H87: Financing | I87: Tampa | J87: FL | K87: Brian Hall | L87: Delivered | M87: 2027-02
A88: 89 | B88: Data inválida | C88: Natalie Brooks | D88: Taycan 4S | E88: 2025 | F88: 132700 | G88: 0 | H88: Wire Transfer | I88: Denver | J88: CO | K88: Jessica White | L88: In Transit
A89: 90 | B89: 2027-03-05 | C89: Brandon Parker | D89: Panamera | E89: 2021 | F89: 81000 | G89: 42 | H89: Cash | I89: Austin | J89: TX | K89: Thomas King | L89: Delivered | M89: 2027-03
A90: 91 | B90: 2027-03-18 | C90: Lauren Foster | D90: 718 Cayman | E90: 2023 | F90: 78900 | G90: 17500 | H90: Debit Card | I90: Seattle | J90: WA | K90: Victor Lee | L90: Cancelled | M90: 2027-03
A91: 92 | B91: 2027-04-02 | C91: Adam Hughes | D91: 911 Turbo S | E91: 2026 | F91: 249300 | G91: 900 | H91: Wire Transfer | I91: Boston | J91: MA | K91: Monica Green | L91: Awaiting Delivery | M91: 2027-04
A92: 93 | B92: Data inválida | C92: Julia Coleman | D92: Cayenne Coupe | E92: 2024 | F92: 108750 | G92: 5530 | H92: Wire Transfer | I92: Phoenix | J92: AZ | K92: Gregory Adams | L92: Pending Approval
A93: 94 | B93: Data inválida | C93: Caleb Simmons | D93: Macan Electric | E93: 2026 | F93: 92600 | G93: 0 | H93: Financing | I93: Chicago | J93: IL | K93: Laura West | L93: Shipped
A94: 95 | B94: 2027-05-12 | C94: Ariana Price | D94: Taycan Turbo | E94: 2025 | F94: 164000 | G94: 0 | H94: ACH Payment | I94: Dallas | J94: TX | K94: Henry King | L94: In Transit | M94: 2027-05
A95: 96 | B95: 2027-05-27 | C95: Owen Rivera | D95: Panamera 4S | E95: 2024 | F95: 119000 | G95: 13400 | H95: Credit Card | I95: San Francisco | J95: CA | K95: Amber Clark | L95: Delivered | M95: 2027-05
A96: 97 | B96: Data inválida | C96: Nora Bennett | D96: 911 GT3 | E96: 2026 | F96: 232500 | G96: 1700 | H96: Wire Transfer | I96: Las Vegas | J96: NV | K96: Peter Lane | L96: Pending
A97: 98 | B97: 2027-06-18 | C97: Isaac Turner | D97: Cayenne E-Hybrid | E97: 2023 | F97: 96800 | G97: 14000 | H97: Lease | I97: Charlotte | J97: NC | K97: Grace Morris | L97: Delivered | M97: 2027-06
A98: 99 | B98: 2027-07-03 | C98: Leah Scott | D98: Macan T | E98: 2022 | F98: 74400 | G98: 20750 | H98: Cash | I98: Mesa | J98: AZ | K98: Kyle Perry | L98: Awaiting Pickup | M98: 2027-07
A99: 100 | B99: 2027-07-22 | C99: Christian Bailey | D99: Taycan GTS | E99: 2025 | F99: 148500 | G99: 5200 | H99: Crypto Payment | I99: Atlanta | J99: GA | K99: Megan Reed | L99: Delivered | M99: 2027-07
A100: 101 | B100: 2027-08-08 | C100: Audrey Russell | D100: 718 Boxster | E100: 2021 | F100: 71900 | G100: 29600 | H100: Bank Transfer | I100: Long Beach | J100: CA | K100: Carl Simmons | L100: Pending | M100: 2027-08
...

Sheet Qualidade_Dados
A1: 🔍 Qualidade dos Dados — Relatório do Agente
A2: << Voltar ao Dashboard
A4: Acurácia por Campo (vs. gabarito de referência da base)
A5: Campo | B5: Acurácia | C5: Divergências
A6: Data da venda | B6: 1 | C6: 0
A7: Ano do modelo | B7: 1 | C7: 0
A8: Preço de venda | B8: 1 | C8: 0
A9: Quilometragem | B9: 1 | C9: 0
A10: Forma de pagamento | B10: 1 | C10: 0
A11: Cidade | B11: 1 | C11: 0
A12: Estado (UF) | B12: 1 | C12: 0
A13: Status de entrega | B13: 1 | C13: 0
A15: Nomes de cliente/vendedor (customer_name, salesperson) não têm coluna de gabarito na base original; a limpeza aplicada (Title Case + correção de hífen + reconciliação de vendedores com apenas o primeiro nome) foi validada manualmente — ver seção abaixo.
A19: Datas Marcadas como Inválidas (24 registros)
A20: ID Venda | B20: Data bruta original
A21: 6 | B21: 2024-02-30
A22: 9 | B22: April 31st, 2024
A23: 13 | B23: 2024/15/07
A24: 17 | B24: 2024-10-40
A25: 22 | B25: 01/32/2025
A26: 24 | B26: February 29th, 2025
A27: 28 | B27: 2025/04/31
A28: 31 | B28: 06/31/2025
A29: 36 | B29: 2025-09-31
A30: 43 | B30: 2025/18/11
A31: 44 | B31: November 31st, 2025
A32: 47 | B32: 2025-12-40
... A44: 102 | B44: August 32nd, 2027
A46: Estas datas correspondem a valores impossíveis no calendário (ex.: 30 de fevereiro, mês 15, dia 40) ou a formatos ambíguos demais para interpretar com segurança. O agente optou por sinalizar como inválidas em vez de adivinhar — essas vendas permanecem no dashboard (contam para faturamento e unidades), mas ficam de fora dos gráficos que dependem de data (ex.: faturamento mensal).
A51: Reconciliação de Vendedores (nome incompleto → nome completo)
A52: Nome bruto | B52: Nome reconciliado
A53: jessica | B53: Jessica White
A54: kevin | B54: Kevin Brown
A55: monica | B55: Monica Green
A56: natalie | B56: Natalie (sem correspondência única — mantido como está)
A58: Quando um vendedor aparece em algumas linhas só com o primeiro nome (ex.: 'kevin') e existe exatamente UM nome completo compatível na base (ex.: 'Kevin Brown'), o agente reconcilia os dois registros como a mesma pessoa. Quando há ambiguidade ou nenhuma correspondência (ex.: 'natalie', sem nenhuma 'Natalie Sobrenome' na base), o nome é mantido como veio, para não inventar dados.

Sheet Resumo
A1: 📊 Tabelas de Apoio (calculadas a partir da aba Dados_Tratados)
A2: << Voltar ao Dashboard
A4: Faturamento por Ano | E4: Faturamento por Forma de Pagamento | I4: Pedidos por Status de Entrega | M4: Faturamento por Modelo (base) | Q4: Faturamento por Estado (base) | Y4: Faturamento por Vendedor (base)
A5: Ano | B5: Faturamento (R$) | E5: Forma de Pagamento | F5: Faturamento (R$) | I5: Status | J5: Pedidos | M5: Modelo | N5: Faturamento (R$) | Q5: UF | R5: Faturamento (R$) | Y5: Vendedor | Z5: Faturamento (R$)
A6: 2024 | B6: =SUMPRODUCT((LEFT(Dados_Tratados!$M$5:$M$104,4)=TEXT(A6,"0"))*Dados_Tratados!$F$5:$F$104) -> 1439050.5 | E6: Cash | F6: =SUMIF(Dados_Tratados!$H$5:$H$104,E6,Dados_Tratados!$F$5:$F$104) -> 1326550 | I6: Delivered | J6: =COUNTIF(Dados_Tratados!$L$5:$L$104,I6) -> 41 | M6: 718 Boxster | N6: =SUMIF(Dados_Tratados!$D$5:$D$104,M6,Dados_Tratados!$F$5:$F$104) -> 219400 | Q6: AK | R6: =SUMIF(Dados_Tratados!$J$5:$J$104,Q6,Dados_Tratados!$F$5:$F$104) -> 132000 | Y6: Alan Price | Z6: =SUMIF(Dados_Tratados!$K$5:$K$104,Y6,Dados_Tratados!$F$5:$F$104) -> 116900
A7: 2025 | B7: =SUMPRODUCT((LEFT(Dados_Tratados!$M$5:$M$104,4)=TEXT(A7,"0"))*Dados_Tratados!$F$5:$F$104) -> 2167500 | E7: Credit Card | F7: =SUMIF(Dados_Tratados!$H$5:$H$104,E7,Dados_Tratados!$F$5:$F$104) -> 1987700 | I7: Shipped | J7: =COUNTIF(Dados_Tratados!$L$5:$L$104,I7) -> 4 | M7: 718 Boxster GTS | N7: =SUMIF(Dados_Tratados!$D$5:$D$104,M7,Dados_Tratados!$F$5:$F$104) -> 91500 | Q7: AZ | R7: =SUMIF(Dados_Tratados!$J$5:$J$104,Q7,Dados_Tratados!$F$5:$F$104) -> 695950 | Y7: Amanda Lee | Z7: =SUMIF(Dados_Tratados!$K$5:$K$104,Y7,Dados_Tratados!$F$5:$F$104) -> 84500
A8: 2026 | B8: =SUMPRODUCT((LEFT(Dados_Tratados!$M$5:$M$104,4)=TEXT(A8,"0"))*Dados_Tratados!$F$5:$F$104) -> 3901150 | E8: Debit Card | F8: =SUMIF(Dados_Tratados!$H$5:$H$104,E8,Dados_Tratados!$F$5:$F$104) -> 326350 | I8: In Transit | J8: =COUNTIF(Dados_Tratados!$L$5:$L$104,I8) -> 15 | M8: 718 Cayman | N8: =SUMIF(Dados_Tratados!$D$5:$D$104,M8,Dados_Tratados!$F$5:$F$104) -> 228300 | Q8: CA | R8: =SUMIF(Dados_Tratados!$J$5:$J$104,Q8,Dados_Tratados!$F$5:$F$104) -> 1973350 | Y8: Amanda Scott | Z8: =SUMIF(Dados_Tratados!$K$5:$K$104,Y8,Dados_Tratados!$F$5:$F$104) -> 235000
A9: 2027 | B9: =SUMPRODUCT((LEFT(Dados_Tratados!$M$5:$M$104,4)=TEXT(A9,"0"))*Dados_Tratados!$F$5:$F$104) -> 1979000 | E9: Bank Transfer | F9: =SUMIF(Dados_Tratados!$H$5:$H$104,E9,Dados_Tratados!$F$5:$F$104) -> 900500 | I9: Awaiting Pickup | J9: =COUNTIF(Dados_Tratados!$L$5:$L$104,I9) -> 4 | M9: 718 Cayman GT4 RS | N9: =SUMIF(Dados_Tratados!$D$5:$D$104,M9,Dados_Tratados!$F$5:$F$104) -> 350000 | Q9: CO | R9: =SUMIF(Dados_Tratados!$J$5:$J$104,Q9,Dados_Tratados!$F$5:$F$104) -> 337600 | Y9: Amber Clark | Z9: =SUMIF(Dados_Tratados!$K$5:$K$104,Y9,Dados_Tratados!$F$5:$F$104) -> 255000
E10: Wire Transfer | F10: =SUMIF(Dados_Tratados!$H$5:$H$104,E10,Dados_Tratados!$F$5:$F$104) -> 3979450 | I10: Awaiting Delivery | J10: =COUNTIF(Dados_Tratados!$L$5:$L$104,I10) -> 5 | M10: 718 Cayman S | N10: =SUMIF(Dados_Tratados!$D$5:$D$104,M10,Dados_Tratados!$F$5:$F$104) -> 82750 | Q10: FL | R10: =SUMIF(Dados_Tratados!$J$5:$J$104,Q10,Dados_Tratados!$F$5:$F$104) -> 566600 | Y10: Angela Green | Z10: =SUMIF(Dados_Tratados!$K$5:$K$104,Y10,Dados_Tratados!$F$5:$F$104) -> 263600
E11: ACH Payment | F11: =SUMIF(Dados_Tratados!$H$5:$H$104,E11,Dados_Tratados!$F$5:$F$104) -> 543000.5 | I11: Pending | J11: =COUNTIF(Dados_Tratados!$L$5:$L$104,I11) -> 17 | M11: 718 Spyder RS | N11: =SUMIF(Dados_Tratados!$D$5:$D$104,M11,Dados_Tratados!$F$5:$F$104) -> 333000 | Q11: GA | R11: =SUMIF(Dados_Tratados!$J$5:$J$104,Q11,Dados_Tratados!$F$5:$F$104) -> 434800 | Y11: Angela Moore | Z11: =SUMIF(Dados_Tratados!$K$5:$K$104,Y11,Dados_Tratados!$F$5:$F$104) -> 176400
E12: Financing | F12: =SUMIF(Dados_Tratados!$H$5:$H$104,E12,Dados_Tratados!$F$5:$F$104) -> 1426650 | I12: Pending Approval | J12: =COUNTIF(Dados_Tratados!$L$5:$L$104,I12) -> 4 | M12: 911 Carrera | N12: =SUMIF(Dados_Tratados!$D$5:$D$104,M12,Dados_Tratados!$F$5:$F$104) -> 251400 | Q12: HI | R12: =SUMIF(Dados_Tratados!$J$5:$J$104,Q12,Dados_Tratados!$F$5:$F$104) -> 104600 | Y12: Betty James | Z12: =SUMIF(Dados_Tratados!$K$5:$K$104,Y12,Dados_Tratados!$F$5:$F$104) -> 268900
E13: Lease | F13: =SUMIF(Dados_Tratados!$H$5:$H$104,E13,Dados_Tratados!$F$5:$F$104) -> 1254600 | I13: Pending Review | J13: =COUNTIF(Dados_Tratados!$L$5:$L$104,I13) -> 2 | M13: 911 Carrera Cabriolet | N13: =SUMIF(Dados_Tratados!$D$5:$D$104,M13,Dados_Tratados!$F$5:$F$104) -> 259800 | Q13: ID | R13: =SUMIF(Dados_Tratados!$J$5:$J$104,Q13,Dados_Tratados!$F$5:$F$104) -> 224000 | Y13: Betty Ward | Z13: =SUMIF(Dados_Tratados!$K$5:$K$104,Y13,Dados_Tratados!$F$5:$F$104) -> 76800
E14: Crypto Payment | F14: =SUMIF(Dados_Tratados!$H$5:$H$104,E14,Dados_Tratados!$F$5:$F$104) -> 1083000 | I14: Awaiting Review | J14: =COUNTIF(Dados_Tratados!$L$5:$L$104,I14) -> 1 | M14: 911 Carrera GTS | N14: =SUMIF(Dados_Tratados!$D$5:$D$104,M14,Dados_Tratados!$F$5:$F$104) -> 241650 | Q14: IL | R14: =SUMIF(Dados_Tratados!$J$5:$J$104,Q14,Dados_Tratados!$F$5:$F$104) -> 166100 | Y14: Brian Allen | Z14: =SUMIF(Dados_Tratados!$K$5:$K$104,Y14,Dados_Tratados!$F$5:$F$104) -> 99950
I15: Cancelled | J15: =COUNTIF(Dados_Tratados!$L$5:$L$104,I15) -> 7 | M15: 911 Carrera S | N15: =SUMIF(Dados_Tratados!$D$5:$D$104,M15,Dados_Tratados!$F$5:$F$104) -> 200900 | Q15: IN | R15: =SUMIF(Dados_Tratados!$J$5:$J$104,Q15,Dados_Tratados!$F$5:$F$104) -> 119900 | Y15: Brian Hall | Z15: =SUMIF(Dados_Tratados!$K$5:$K$104,Y15,Dados_Tratados!$F$5:$F$104) -> 182550
M16: 911 Dakar | N16: =SUMIF(Dados_Tratados!$D$5:$D$104,M16,Dados_Tratados!$F$5:$F$104) -> 810600 | Q16: KS | R16: =SUMIF(Dados_Tratados!$J$5:$J$104,Q16,Dados_Tratados!$F$5:$F$104) -> 351600 | Y16: Carl Simmons | Z16: =SUMIF(Dados_Tratados!$K$5:$K$104,Y16,Dados_Tratados!$F$5:$F$104) -> 141800
M17: 911 GT3 | N17: =SUMIF(Dados_Tratados!$D$5:$D$104,M17,Dados_Tratados!$F$5:$F$104) -> 697500 | Q17: KY | R17: =SUMIF(Dados_Tratados!$J$5:$J$104,Q17,Dados_Tratados!$F$5:$F$104) -> 169000 | Y17: Chris Moore | Z17: =SUMIF(Dados_Tratados!$K$5:$K$104,Y17,Dados_Tratados!$F$5:$F$104) -> 141650
M18: 911 GT3 RS | N18: =SUMIF(Dados_Tratados!$D$5:$D$104,M18,Dados_Tratados!$F$5:$F$104) -> 286500 | Q18: LA | R18: =SUMIF(Dados_Tratados!$J$5:$J$104,Q18,Dados_Tratados!$F$5:$F$104) -> 361400 | Y18: Diana Cooper | Z18: =SUMIF(Dados_Tratados!$K$5:$K$104,Y18,Dados_Tratados!$F$5:$F$104) -> 202300
M19: 911 Targa 4 | N19: =SUMIF(Dados_Tratados!$D$5:$D$104,M19,Dados_Tratados!$F$5:$F$104) -> 284500 | Q19: MA | R19: =SUMIF(Dados_Tratados!$J$5:$J$104,Q19,Dados_Tratados!$F$5:$F$104) -> 328800 | Y19: Diana Long | Z19: =SUMIF(Dados_Tratados!$K$5:$K$104,Y19,Dados_Tratados!$F$5:$F$104) -> 351600
M20: 911 Targa 4S | N20: =SUMIF(Dados_Tratados!$D$5:$D$104,M20,Dados_Tratados!$F$5:$F$104) -> 315250 | Q20: MI | R20: =SUMIF(Dados_Tratados!$J$5:$J$104,Q20,Dados_Tratados!$F$5:$F$104) -> 76800 | Y20: Eric Woods | Z20: =SUMIF(Dados_Tratados!$K$5:$K$104,Y20,Dados_Tratados!$F$5:$F$104) -> 98200
M21: 911 Turbo | N21: =SUMIF(Dados_Tratados!$D$5:$D$104,M21,Dados_Tratados!$F$5:$F$104) -> 198300 | Q21: MN | R21: =SUMIF(Dados_Tratados!$J$5:$J$104,Q21,Dados_Tratados!$F$5:$F$104) -> 158750 | Y21: Frank Morgan | Z21: =SUMIF(Dados_Tratados!$K$5:$K$104,Y21,Dados_Tratados!$F$5:$F$104) -> 214000
M22: 911 Turbo S | N22: =SUMIF(Dados_Tratados!$D$5:$D$104,M22,Dados_Tratados!$F$5:$F$104) -> 726300 | Q22: MO | R22: =SUMIF(Dados_Tratados!$J$5:$J$104,Q22,Dados_Tratados!$F$5:$F$104) -> 178750 | Y22: Frank Reed | Z22: =SUMIF(Dados_Tratados!$K$5:$K$104,Y22,Dados_Tratados!$F$5:$F$104) -> 132000
M23: Cayenne | N23: =SUMIF(Dados_Tratados!$D$5:$D$104,M23,Dados_Tratados!$F$5:$F$104) -> 239700 | Q23: NC | R23: =SUMIF(Dados_Tratados!$J$5:$J$104,Q23,Dados_Tratados!$F$5:$F$104) -> 510100 | Y23: Gary Price | Z23: =SUMIF(Dados_Tratados!$K$5:$K$104,Y23,Dados_Tratados!$F$5:$F$104) -> 101300
M24: Cayenne Coupe | N24: =SUMIF(Dados_Tratados!$D$5:$D$104,M24,Dados_Tratados!$F$5:$F$104) -> 436250 | Q24: NE | R24: =SUMIF(Dados_Tratados!$J$5:$J$104,Q24,Dados_Tratados!$F$5:$F$104) -> 292000 | Y24: Gary Reed | Z24: =SUMIF(Dados_Tratados!$K$5:$K$104,Y24,Dados_Tratados!$F$5:$F$104) -> 173600
M25: Cayenne E-Hybrid | N25: =SUMIF(Dados_Tratados!$D$5:$D$104,M25,Dados_Tratados!$F$5:$F$104) -> 373650 | Q25: NJ | R25: =SUMIF(Dados_Tratados!$J$5:$J$104,Q25,Dados_Tratados!$F$5:$F$104) -> 208450 | Y25: George Bell | Z25: =SUMIF(Dados_Tratados!$K$5:$K$104,Y25,Dados_Tratados!$F$5:$F$104) -> 73500
M26: Cayenne S | N26: =SUMIF(Dados_Tratados!$D$5:$D$104,M26,Dados_Tratados!$F$5:$F$104) -> 289450 | Q26: NM | R26: =SUMIF(Dados_Tratados!$J$5:$J$104,Q26,Dados_Tratados!$F$5:$F$104) -> 198300 | Y26: George Hall | Z26: =SUMIF(Dados_Tratados!$K$5:$K$104,Y26,Dados_Tratados!$F$5:$F$104) -> 121750
M27: Cayenne Turbo | N27: =SUMIF(Dados_Tratados!$D$5:$D$104,M27,Dados_Tratados!$F$5:$F$104) -> 146800 | Q27: NV | R27: =SUMIF(Dados_Tratados!$J$5:$J$104,Q27,Dados_Tratados!$F$5:$F$104) -> 643400 | Y27: Grace Morris | Z27: =SUMIF(Dados_Tratados!$K$5:$K$104,Y27,Dados_Tratados!$F$5:$F$104) -> 189600
... M38: Panamera Turbo | N38: =SUMIF(Dados_Tratados!$D$5:$D$104,M38,Dados_Tratados!$F$5:$F$104) -> 273500 | Q38: WI | R38: =SUMIF(Dados_Tratados!$J$5:$J$104,Q38,Dados_Tratados!$F$5:$F$104) -> 211200 | Y38: Karen Stone | Z38: =SUMIF(Dados_Tratados!$K$5:$K$104,Y38,Dados_Tratados!$F$5:$F$104) -> 78400
M39: Panamera Turbo S | N39: =SUMIF(Dados_Tratados!$D$5:$D$104,M39,Dados_Tratados!$F$5:$F$104) -> 266000 | Y39: Kevin Brown | Z39: =SUMIF(Dados_Tratados!$K$5:$K$104,Y39,Dados_Tratados!$F$5:$F$104) -> 206400
M40: Taycan | N40: =SUMIF(Dados_Tratados!$D$5:$D$104,M40,Dados_Tratados!$F$5:$F$104) -> 236800 | Y40: Kyle Perry | Z40: =SUMIF(Dados_Tratados!$K$5:$K$104,Y40,Dados_Tratados!$F$5:$F$104) -> 146800
M41: Taycan 4S | N41: =SUMIF(Dados_Tratados!$D$5:$D$104,M41,Dados_Tratados!$F$5:$F$104) -> 514300 | Q41: Top 10 Estados por Faturamento | Y41: Laura Hill | Z41: =SUMIF(Dados_Tratados!$K$5:$K$104,Y41,Dados_Tratados!$F$5:$F$104) -> 255300
M42: Taycan Cross Turismo | N42: =SUMIF(Dados_Tratados!$D$5:$D$104,M42,Dados_Tratados!$F$5:$F$104) -> 246400 | Q42: UF | R42: Faturamento (R$) | Y42: Laura West | Z42: =SUMIF(Dados_Tratados!$K$5:$K$104,Y42,Dados_Tratados!$F$5:$F$104) -> 186200
M43: Taycan GTS | N43: =SUMIF(Dados_Tratados!$D$5:$D$104,M43,Dados_Tratados!$F$5:$F$104) -> 429500 | Q43: =INDEX($Q$6:$Q$38,MATCH(R43,$R$6:$R$38,0)) -> TX | R43: =LARGE($R$6:$R$38,1) -> 2023400.5 | Y43: Linda Cole | Z43: =SUMIF(Dados_Tratados!$K$5:$K$104,Y43,Dados_Tratados!$F$5:$F$104) -> 284500
M44: Taycan Turbo | N44: =SUMIF(Dados_Tratados!$D$5:$D$104,M44,Dados_Tratados!$F$5:$F$104) -> 475700.5 | Q44: =INDEX($Q$6:$Q$38,MATCH(R44,$R$6:$R$38,0)) -> CA | R44: =LARGE($R$6:$R$38,2) -> 1973350 | Y44: Lisa Dunn | Z44: =SUMIF(Dados_Tratados!$K$5:$K$104,Y44,Dados_Tratados!$F$5:$F$104) -> 218000
M45: Taycan Turbo S | N45: =SUMIF(Dados_Tratados!$D$5:$D$104,M45,Dados_Tratados!$F$5:$F$104) -> 432000 | Q45: =INDEX($Q$6:$Q$38,MATCH(R45,$R$6:$R$38,0)) -> AZ | R45: =LARGE($R$6:$R$38,3) -> 695950 | Y45: Lisa Ray | Z45: =SUMIF(Dados_Tratados!$K$5:$K$104,Y45,Dados_Tratados!$F$5:$F$104) -> 104500
Q46: =INDEX($Q$6:$Q$38,MATCH(R46,$R$6:$R$38,0)) -> NV | R46: =LARGE($R$6:$R$38,4) -> 643400 | Y46: Maria Foster | Z46: =SUMIF(Dados_Tratados!$K$5:$K$104,Y46,Dados_Tratados!$F$5:$F$104) -> 119900
Q47: =INDEX($Q$6:$Q$38,MATCH(R47,$R$6:$R$38,0)) -> FL | R47: =LARGE($R$6:$R$38,5) -> 566600 | Y47: Maria Green | Z47: =SUMIF(Dados_Tratados!$K$5:$K$104,Y47,Dados_Tratados!$F$5:$F$104) -> 66750
M48: Top 10 Modelos por Faturamento | Q48: =INDEX($Q$6:$Q$38,MATCH(R48,$R$6:$R$38,0)) -> OH | R48: =LARGE($R$6:$R$38,6) -> 523850 | Y48: Mark Evans | Z48: =SUMIF(Dados_Tratados!$K$5:$K$104,Y48,Dados_Tratados!$F$5:$F$104) -> 96300
M49: Modelo | N49: Faturamento (R$) | Q49: =INDEX($Q$6:$Q$38,MATCH(R49,$R$6:$R$38,0)) -> NC | R49: =LARGE($R$6:$R$38,7) -> 510100 | Y49: Martin Brooks | Z49: =SUMIF(Dados_Tratados!$K$5:$K$104,Y49,Dados_Tratados!$F$5:$F$104) -> 209000
M50: =INDEX($M$6:$M$45,MATCH(N50,$N$6:$N$45,0)) -> 911 Dakar | N50: =LARGE($N$6:$N$45,1) -> 810600 | Q50: =INDEX($Q$6:$Q$38,MATCH(R50,$R$6:$R$38,0)) -> GA | R50: =LARGE($R$6:$R$38,8) -> 434800 | Y50: Martin Young | Z50: =SUMIF(Dados_Tratados!$K$5:$K$104,Y50,Dados_Tratados!$F$5:$F$104) -> 198400
M51: =INDEX($M$6:$M$45,MATCH(N51,$N$6:$N$45,0)) -> 911 Turbo S | N51: =LARGE($N$6:$N$45,2) -> 726300 | Q51: =INDEX($Q$6:$Q$38,MATCH(R51,$R$6:$R$38,0)) -> LA | R51: =LARGE($R$6:$R$38,9) -> 361400 | Y51: Megan Reed | Z51: =SUMIF(Dados_Tratados!$K$5:$K$104,Y51,Dados_Tratados!$F$5:$F$104) -> 307000
M52: =INDEX($M$6:$M$45,MATCH(N52,$N$6:$N$45,0)) -> 911 GT3 | N52: =LARGE($N$6:$N$45,3) -> 697500 | Q52: =INDEX($Q$6:$Q$38,MATCH(R52,$R$6:$R$38,0)) -> VA | R52: =LARGE($R$6:$R$38,10) -> 358700 | Y52: Monica Green | Z52: =SUMIF(Dados_Tratados!$K$5:$K$104,Y52,Dados_Tratados!$F$5:$F$104) -> 447600
M53: =INDEX($M$6:$M$45,MATCH(N53,$N$6:$N$45,0)) -> Cayenne Turbo GT | N53: =LARGE($N$6:$N$45,4) -> 592800 | Y53: Nancy Reed | Z53: =SUMIF(Dados_Tratados!$K$5:$K$104,Y53,Dados_Tratados!$F$5:$F$104) -> 89750
M54: =INDEX($M$6:$M$45,MATCH(N54,$N$6:$N$45,0)) -> Taycan 4S | N54: =LARGE($N$6:$N$45,5) -> 514300 | Y54: Natalie | Z54: =SUMIF(Dados_Tratados!$K$5:$K$104,Y54,Dados_Tratados!$F$5:$F$104) -> 124500
M55: =INDEX($M$6:$M$45,MATCH(N55,$N$6:$N$45,0)) -> Taycan Turbo | N55: =LARGE($N$6:$N$45,6) -> 475700.5 | Y55: Olivia Cruz | Z55: =SUMIF(Dados_Tratados!$K$5:$K$104,Y55,Dados_Tratados!$F$5:$F$104) -> 104600
M56: =INDEX($M$6:$M$45,MATCH(N56,$N$6:$N$45,0)) -> Cayenne Coupe | N56: =LARGE($N$6:$N$45,7) -> 436250 | Y56: Olivia Ross | Z56: =SUMIF(Dados_Tratados!$K$5:$K$104,Y56,Dados_Tratados!$F$5:$F$104) -> 191900
M57: =INDEX($M$6:$M$45,MATCH(N57,$N$6:$N$45,0)) -> Taycan Turbo S | N57: =LARGE($N$6:$N$45,8) -> 432000 | Y57: Patricia Fox | Z57: =SUMIF(Dados_Tratados!$K$5:$K$104,Y57,Dados_Tratados!$F$5:$F$104) -> 67500
M58: =INDEX($M$6:$M$45,MATCH(N58,$N$6:$N$45,0)) -> Taycan GTS | N58: =LARGE($N$6:$N$45,9) -> 429500 | Y58: Patrick Wood | Z58: =SUMIF(Dados_Tratados!$K$5:$K$104,Y58,Dados_Tratados!$F$5:$F$104) -> 301700
M59: =INDEX($M$6:$M$45,MATCH(N59,$N$6:$N$45,0)) -> Cayenne E-Hybrid | N59: =LARGE($N$6:$N$45,10) -> 373650 | Y59: Peter Ford | Z59: =SUMIF(Dados_Tratados!$K$5:$K$104,Y59,Dados_Tratados!$F$5:$F$104) -> 337800
Y60: Peter Lane | Z60: =SUMIF(Dados_Tratados!$K$5:$K$104,Y60,Dados_Tratados!$F$5:$F$104) -> 519000
Y61: Rachel Turner | Z61: =SUMIF(Dados_Tratados!$K$5:$K$104,Y61,Dados_Tratados!$F$5:$F$104) -> 369800
Y62: Rachel West | Z62: =SUMIF(Dados_Tratados!$K$5:$K$104,Y62,Dados_Tratados!$F$5:$F$104) -> 108500
Y63: Samuel Price | Z63: =SUMIF(Dados_Tratados!$K$5:$K$104,Y63,Dados_Tratados!$F$5:$F$104) -> 287200.5
Y64: Sandra Hill | Z64: =SUMIF(Dados_Tratados!$K$5:$K$104,Y64,Dados_Tratados!$F$5:$F$104) -> 112000
Y65: Steve Gray | Z65: =SUMIF(Dados_Tratados!$K$5:$K$104,Y65,Dados_Tratados!$F$5:$F$104) -> 315250
Y66: Steve Ross | Z66: =SUMIF(Dados_Tratados!$K$5:$K$104,Y66,Dados_Tratados!$F$5:$F$104) -> 361400
Y67: Teresa Cook | Z67: =SUMIF(Dados_Tratados!$K$5:$K$104,Y67,Dados_Tratados!$F$5:$F$104) -> 82000
Y68: Teresa Ward | Z68: =SUMIF(Dados_Tratados!$K$5:$K$104,Y68,Dados_Tratados!$F$5:$F$104) -> 200000
Y69: Thomas Fox | Z69: =SUMIF(Dados_Tratados!$K$5:$K$104,Y69,Dados_Tratados!$F$5:$F$104) -> 59000
Y70: Thomas King | Z70: =SUMIF(Dados_Tratados!$K$5:$K$104,Y70,Dados_Tratados!$F$5:$F$104) -> 202000
Y71: Victor Lee | Z71: =SUMIF(Dados_Tratados!$K$5:$K$104,Y71,Dados_Tratados!$F$5:$F$104) -> 152900
Y72: Victor Stone | Z72: =SUMIF(Dados_Tratados!$K$5:$K$104,Y72,Dados_Tratados!$F$5:$F$104) -> 282300
Y75: Top 10 Vendedores por Faturamento
Y76: Vendedor | Z76: Faturamento (R$)
Y77: =INDEX($Y$6:$Y$72,MATCH(Z77,$Z$6:$Z$72,0)) -> Peter Lane | Z77: =LARGE($Z$6:$Z$72,1) -> 519000
Y78: =INDEX($Y$6:$Y$72,MATCH(Z78,$Z$6:$Z$72,0)) -> Karen Diaz | Z78: =LARGE($Z$6:$Z$72,2) -> 494000
Y79: =INDEX($Y$6:$Y$72,MATCH(Z79,$Z$6:$Z$72,0)) -> Monica Green | Z79: =LARGE($Z$6:$Z$72,3) -> 447600
Y80: =INDEX($Y$6:$Y$72,MATCH(Z80,$Z$6:$Z$72,0)) -> Rachel Turner | Z80: =LARGE($Z$6:$Z$72,4) -> 369800
Y81: =INDEX($Y$6:$Y$72,MATCH(Z81,$Z$6:$Z$72,0)) -> Steve Ross | Z81: =LARGE($Z$6:$Z$72,5) -> 361400
Y82: =INDEX($Y$6:$Y$72,MATCH(Z82,$Z$6:$Z$72,0)) -> Diana Long | Z82: =LARGE($Z$6:$Z$72,6) -> 351600
Y83: =INDEX($Y$6:$Y$72,MATCH(Z83,$Z$6:$Z$72,0)) -> Peter Ford | Z83: =LARGE($Z$6:$Z$72,7) -> 337800
Y84: =INDEX($Y$6:$Y$72,MATCH(Z84,$Z$6:$Z$72,0)) -> Steve Gray | Z84: =LARGE($Z$6:$Z$72,8) -> 315250
Y85: =INDEX($Y$6:$Y$72,MATCH(Z85,$Z$6:$Z$72,0)) -> Megan Reed | Z85: =LARGE($Z$6:$Z$72,9) -> 307000
Y86: =INDEX($Y$6:$Y$72,MATCH(Z86,$Z$6:$Z$72,0)) -> Patrick Wood | Z86: =LARGE($Z$6:$Z$72,10) -> 301700

Sheet Dashboard
A1: 🏎️ Dashboard de Vendas — Porsche
A2: Painel de indicadores comerciais gerado a partir da base tratada pelo Agente de Tratamento de Dados (ver abas Dados_Tratados e Qualidade_Dados)
A4: FATURAMENTO TOTAL | D4: VEÍCULOS VENDIDOS | G4: TICKET MÉDIO | J4: KM MÉDIA RODADA
A5: =SUM(Dados_Tratados!$F$5:$F$104) -> 12827800 | D5: =COUNTA(Dados_Tratados!$A$5:$A$104) -> 100 | G5: =SUM(Dados_Tratados!$F$5:$F$104)/COUNTA(Dados_Tratados!$A$5:$A$104) -> 128278.01 | J5: =AVERAGE(Dados_Tratados!$G$5:$G$104) -> 11422.1
A7: MODELO MAIS VENDIDO (R$) | E7: ESTADO LÍDER (UF) | H7: DATAS VÁLIDAS
A8: =Resumo!M50 -> 911 Dakar | E8: =Resumo!Q43 -> TX | H8: =TEXT((COUNTA(Dados_Tratados!$A$5:$A$104)-COUNTIF(Dados_Tratados!$B$5:$B$104,"Data inválida"))/COUNTA(Dados_Tratados!$A$5:$A$104),"0.0%") & " (" & COUNTIF(Dados_Tratados!$B$5:$B$104,"Data inválida") & " p/ revisar)" -> 76.0% (24 p/ revisar)
A65: Todos os indicadores e gráficos são calculados a partir da aba "Dados_Tratados" (saída do Agente de Tratamento de Dados), agregada na aba "Resumo". Os KPIs de faturamento consideram TODAS as vendas, mesmo as com data inválida; os gráficos que dependem de data/ano excluem essas vendas — ver aba Qualidade_Dados para o detalhamento. Para atualizar, gere uma nova base tratada executando agente_tratamento_dados.py sobre uma base bruta atualizada.
